telegram_logging/__init__.py
telegram_logging/telegram.py
telegram_logging-1.0.0.dist-info/LICENSE
telegram_logging-1.0.0.dist-info/METADATA
telegram_logging-1.0.0.dist-info/WHEEL
telegram_logging-1.0.0.dist-info/top_level.txt
telegram_logging-1.0.0.dist-info/RECORD
