Metadata-Version: 2.1
Name: telegram_logging
Version: 1.0.0
Summary: Simple Telegram logging with zero dependencies.
Home-page: https://github.com/lbltavares/telegram-logging
Author: lbltavares
License: MIT
Platform: UNKNOWN
License-File: LICENSE
